{
	"configurations" : 
	[
		{
			"directories" : 
			[
				{
					"build" : ".",
					"jsonFile" : "directory-.-Debug-d0094a50bb2071803777.json",
					"minimumCMakeVersion" : 
					{
						"string" : "3.8"
					},
					"projectIndex" : 0,
					"source" : ".",
					"targetIndexes" : 
					[
						0,
						1
					]
				}
			],
			"name" : "Debug",
			"projects" : 
			[
				{
					"directoryIndexes" : 
					[
						0
					],
					"name" : "SimpleLinkedList",
					"targetIndexes" : 
					[
						0,
						1
					]
				}
			],
			"targets" : 
			[
				{
					"directoryIndex" : 0,
					"id" : "SimpleLinkedList::@6890427a1f51a3e7e1df",
					"jsonFile" : "target-SimpleLinkedList-Debug-9e3b0f66516b8bfdf90d.json",
					"name" : "SimpleLinkedList",
					"projectIndex" : 0
				},
				{
					"directoryIndex" : 0,
					"id" : "runUnitTests::@6890427a1f51a3e7e1df",
					"jsonFile" : "target-runUnitTests-Debug-55caee6de4b31ae4a34d.json",
					"name" : "runUnitTests",
					"projectIndex" : 0
				}
			]
		}
	],
	"kind" : "codemodel",
	"paths" : 
	{
		"build" : "D:/git/SimpleLinkedList/SimpleLinkedList/out/build/x64-debug",
		"source" : "D:/git/SimpleLinkedList/SimpleLinkedList"
	},
	"version" : 
	{
		"major" : 2,
		"minor" : 4
	}
}
